<?xml version="1.0" encoding="UTF-8"?>
<metadata xml:lang="es"><Esri><CreaDate>20200529</CreaDate><CreaTime>12211100</CreaTime><ArcGISFormat>1.0</ArcGISFormat><SyncOnce>TRUE</SyncOnce><DataProperties><lineage><Process ToolSource="c:\program files (x86)\arcgis\desktop10.5\ArcToolbox\Toolboxes\Data Management Tools.tbx\CalculateField" Date="20200529" Time="122111">CalculateField MPM_FuenteCensal_2018 MPM_CAB [MPM_Cabece] VB #</Process><Process ToolSource="c:\program files (x86)\arcgis\desktop10.5\ArcToolbox\Toolboxes\Data Management Tools.tbx\CalculateField" Date="20200529" Time="122131">CalculateField MPM_FuenteCensal_2018 MPM_CPRD [MPM_Cpob_R] VB #</Process><Process ToolSource="c:\program files (x86)\arcgis\desktop10.5\ArcToolbox\Toolboxes\Data Management Tools.tbx\CalculateField" Date="20200529" Time="122221">CalculateField MPM_FuenteCensal_2018 AFBMO_TOT [Analfabeti] VB #</Process><Process ToolSource="c:\program files (x86)\arcgis\desktop10.5\ArcToolbox\Toolboxes\Data Management Tools.tbx\CalculateField" Date="20200529" Time="122234">CalculateField MPM_FuenteCensal_2018 AFBMO_CAB [Anlafabeti] VB #</Process><Process ToolSource="c:\program files (x86)\arcgis\desktop10.5\ArcToolbox\Toolboxes\Data Management Tools.tbx\CalculateField" Date="20200529" Time="122255">CalculateField MPM_FuenteCensal_2018 AFBMO_CPRD [Analfabe_1] VB #</Process><Process ToolSource="c:\program files (x86)\arcgis\desktop10.5\ArcToolbox\Toolboxes\Data Management Tools.tbx\CalculateField" Date="20200529" Time="122330">CalculateField MPM_FuenteCensal_2018 BLE_TOT [BajoLogroE] VB #</Process><Process ToolSource="c:\program files (x86)\arcgis\desktop10.5\ArcToolbox\Toolboxes\Data Management Tools.tbx\CalculateField" Date="20200529" Time="122346">CalculateField MPM_FuenteCensal_2018 BLE_CAB [BajoLogr_1] VB #</Process><Process ToolSource="c:\program files (x86)\arcgis\desktop10.5\ArcToolbox\Toolboxes\Data Management Tools.tbx\CalculateField" Date="20200529" Time="122414">CalculateField MPM_FuenteCensal_2018 BLE_CPRD [BajoLogr_2] VB #</Process><Process ToolSource="c:\program files (x86)\arcgis\desktop10.5\ArcToolbox\Toolboxes\Data Management Tools.tbx\CalculateField" Date="20200529" Time="122439">CalculateField MPM_FuenteCensal_2018 BSCPI_TOT [BarreraSer] VB #</Process><Process ToolSource="c:\program files (x86)\arcgis\desktop10.5\ArcToolbox\Toolboxes\Data Management Tools.tbx\CalculateField" Date="20200529" Time="122502">CalculateField MPM_FuenteCensal_2018 BSCPI_CAB [BarreraS_1] VB #</Process><Process ToolSource="c:\program files (x86)\arcgis\desktop10.5\ArcToolbox\Toolboxes\Data Management Tools.tbx\CalculateField" Date="20200529" Time="122519">CalculateField MPM_FuenteCensal_2018 BSCPI_CPRD [BarreraS_2] VB #</Process><Process ToolSource="c:\program files (x86)\arcgis\desktop10.5\ArcToolbox\Toolboxes\Data Management Tools.tbx\CalculateField" Date="20200529" Time="122549">CalculateField MPM_FuenteCensal_2018 BASS_TOT [BarreraAcc] VB #</Process><Process ToolSource="c:\program files (x86)\arcgis\desktop10.5\ArcToolbox\Toolboxes\Data Management Tools.tbx\CalculateField" Date="20200529" Time="122604">CalculateField MPM_FuenteCensal_2018 BASS_CAB [BarreraA_1] VB #</Process><Process ToolSource="c:\program files (x86)\arcgis\desktop10.5\ArcToolbox\Toolboxes\Data Management Tools.tbx\CalculateField" Date="20200529" Time="122623">CalculateField MPM_FuenteCensal_2018 BASS_CPRD [BarreraA_2] VB #</Process><Process ToolSource="c:\program files (x86)\arcgis\desktop10.5\ArcToolbox\Toolboxes\Data Management Tools.tbx\CalculateField" Date="20200529" Time="122642">CalculateField MPM_FuenteCensal_2018 TDE_TOT [TasaDepend] VB #</Process><Process ToolSource="c:\program files (x86)\arcgis\desktop10.5\ArcToolbox\Toolboxes\Data Management Tools.tbx\CalculateField" Date="20200529" Time="122657">CalculateField MPM_FuenteCensal_2018 TDE_CAB [TasaDepe_1] VB #</Process><Process ToolSource="c:\program files (x86)\arcgis\desktop10.5\ArcToolbox\Toolboxes\Data Management Tools.tbx\CalculateField" Date="20200529" Time="122725">CalculateField MPM_FuenteCensal_2018 TDE_CPRD [TasaDepe_2] VB #</Process><Process ToolSource="c:\program files (x86)\arcgis\desktop10.5\ArcToolbox\Toolboxes\Data Management Tools.tbx\CalculateField" Date="20200529" Time="122750">CalculateField MPM_FuenteCensal_2018 HC_TOT [Hacinamien] VB #</Process><Process ToolSource="c:\program files (x86)\arcgis\desktop10.5\ArcToolbox\Toolboxes\Data Management Tools.tbx\CalculateField" Date="20200529" Time="122816">CalculateField MPM_FuenteCensal_2018 HC_CAB [Hacinami_1] VB #</Process><Process ToolSource="c:\program files (x86)\arcgis\desktop10.5\ArcToolbox\Toolboxes\Data Management Tools.tbx\CalculateField" Date="20200529" Time="122856">CalculateField MPM_FuenteCensal_2018 HC_CPRD [Hacinami_2] VB #</Process><Process ToolSource="c:\program files (x86)\arcgis\desktop10.5\ArcToolbox\Toolboxes\Data Management Tools.tbx\CalculateField" Date="20200529" Time="122922">CalculateField MPM_FuenteCensal_2018 IEE_TOT [Inadecuada] VB #</Process><Process ToolSource="c:\program files (x86)\arcgis\desktop10.5\ArcToolbox\Toolboxes\Data Management Tools.tbx\CalculateField" Date="20200529" Time="123003">CalculateField MPM_FuenteCensal_2018 IEE_CAB [Inadecua_1] VB #</Process><Process ToolSource="c:\program files (x86)\arcgis\desktop10.5\ArcToolbox\Toolboxes\Data Management Tools.tbx\CalculateField" Date="20200529" Time="123022">CalculateField MPM_FuenteCensal_2018 IEE_CPRD [Inadecua_2] VB #</Process><Process ToolSource="c:\program files (x86)\arcgis\desktop10.5\ArcToolbox\Toolboxes\Data Management Tools.tbx\CalculateField" Date="20200529" Time="123107">CalculateField MPM_FuenteCensal_2018 IE_TOT [Inasistenc] VB #</Process><Process ToolSource="c:\program files (x86)\arcgis\desktop10.5\ArcToolbox\Toolboxes\Data Management Tools.tbx\CalculateField" Date="20200529" Time="123132">CalculateField MPM_FuenteCensal_2018 IE_CAB [Inasiste_1] VB #</Process><Process ToolSource="c:\program files (x86)\arcgis\desktop10.5\ArcToolbox\Toolboxes\Data Management Tools.tbx\CalculateField" Date="20200601" Time="082730">CalculateField MPM_FuenteCensal_2018 MPM_CAB [MPM_Cabece] VB #</Process><Process ToolSource="c:\program files (x86)\arcgis\desktop10.5\ArcToolbox\Toolboxes\Data Management Tools.tbx\CalculateField" Date="20200601" Time="082746">CalculateField MPM_FuenteCensal_2018 MPM_CPRD [MPM_Cpob_R] VB #</Process><Process ToolSource="c:\program files (x86)\arcgis\desktop10.5\ArcToolbox\Toolboxes\Data Management Tools.tbx\CalculateField" Date="20200601" Time="082759">CalculateField MPM_FuenteCensal_2018 AFBMO_TOT [Analfabeti] VB #</Process><Process ToolSource="c:\program files (x86)\arcgis\desktop10.5\ArcToolbox\Toolboxes\Data Management Tools.tbx\CalculateField" Date="20200601" Time="082811">CalculateField MPM_FuenteCensal_2018 AFBMO_CAB [Anlafabeti] VB #</Process><Process ToolSource="c:\program files (x86)\arcgis\desktop10.5\ArcToolbox\Toolboxes\Data Management Tools.tbx\CalculateField" Date="20200601" Time="082823">CalculateField MPM_FuenteCensal_2018 AFBMO_CPRD [Analfabe_1] VB #</Process><Process ToolSource="c:\program files (x86)\arcgis\desktop10.5\ArcToolbox\Toolboxes\Data Management Tools.tbx\CalculateField" Date="20200601" Time="082838">CalculateField MPM_FuenteCensal_2018 BLE_TOT [BajoLogroE] VB #</Process><Process ToolSource="c:\program files (x86)\arcgis\desktop10.5\ArcToolbox\Toolboxes\Data Management Tools.tbx\CalculateField" Date="20200601" Time="082851">CalculateField MPM_FuenteCensal_2018 BLE_CAB [BajoLogr_1] VB #</Process><Process ToolSource="c:\program files (x86)\arcgis\desktop10.5\ArcToolbox\Toolboxes\Data Management Tools.tbx\CalculateField" Date="20200601" Time="082902">CalculateField MPM_FuenteCensal_2018 BLE_CPRD [BajoLogr_2] VB #</Process><Process ToolSource="c:\program files (x86)\arcgis\desktop10.5\ArcToolbox\Toolboxes\Data Management Tools.tbx\CalculateField" Date="20200601" Time="085134">CalculateField MPM_FuenteCensal_2018 BSCPI_TOT [BarreraSer] VB #</Process><Process ToolSource="c:\program files (x86)\arcgis\desktop10.5\ArcToolbox\Toolboxes\Data Management Tools.tbx\CalculateField" Date="20200601" Time="085149">CalculateField MPM_FuenteCensal_2018 BSCPI_CAB [BarreraS_1] VB #</Process><Process ToolSource="c:\program files (x86)\arcgis\desktop10.5\ArcToolbox\Toolboxes\Data Management Tools.tbx\CalculateField" Date="20200601" Time="085203">CalculateField MPM_FuenteCensal_2018 BSCPI_CPRD [BarreraS_2] VB #</Process><Process ToolSource="c:\program files (x86)\arcgis\desktop10.5\ArcToolbox\Toolboxes\Data Management Tools.tbx\CalculateField" Date="20200601" Time="085217">CalculateField MPM_FuenteCensal_2018 BASS_TOT [BarreraAcc] VB #</Process><Process ToolSource="c:\program files (x86)\arcgis\desktop10.5\ArcToolbox\Toolboxes\Data Management Tools.tbx\CalculateField" Date="20200601" Time="085232">CalculateField MPM_FuenteCensal_2018 BASS_CAB [BarreraA_1] VB #</Process><Process ToolSource="c:\program files (x86)\arcgis\desktop10.5\ArcToolbox\Toolboxes\Data Management Tools.tbx\CalculateField" Date="20200601" Time="085250">CalculateField MPM_FuenteCensal_2018 BASS_CPRD [BarreraA_2] VB #</Process><Process ToolSource="c:\program files (x86)\arcgis\desktop10.5\ArcToolbox\Toolboxes\Data Management Tools.tbx\CalculateField" Date="20200601" Time="085302">CalculateField MPM_FuenteCensal_2018 TDE_TOT [TasaDepend] VB #</Process><Process ToolSource="c:\program files (x86)\arcgis\desktop10.5\ArcToolbox\Toolboxes\Data Management Tools.tbx\CalculateField" Date="20200601" Time="085314">CalculateField MPM_FuenteCensal_2018 TDE_CAB [TasaDepe_1] VB #</Process><Process ToolSource="c:\program files (x86)\arcgis\desktop10.5\ArcToolbox\Toolboxes\Data Management Tools.tbx\CalculateField" Date="20200601" Time="085324">CalculateField MPM_FuenteCensal_2018 TDE_CPRD [TasaDepe_2] VB #</Process><Process ToolSource="c:\program files (x86)\arcgis\desktop10.5\ArcToolbox\Toolboxes\Data Management Tools.tbx\CalculateField" Date="20200601" Time="085336">CalculateField MPM_FuenteCensal_2018 HC_TOT [Hacinamien] VB #</Process><Process ToolSource="c:\program files (x86)\arcgis\desktop10.5\ArcToolbox\Toolboxes\Data Management Tools.tbx\CalculateField" Date="20200601" Time="085348">CalculateField MPM_FuenteCensal_2018 HC_CAB [Hacinami_1] VB #</Process><Process ToolSource="c:\program files (x86)\arcgis\desktop10.5\ArcToolbox\Toolboxes\Data Management Tools.tbx\CalculateField" Date="20200601" Time="085402">CalculateField MPM_FuenteCensal_2018 HC_CPRD [Hacinami_2] VB #</Process><Process ToolSource="c:\program files (x86)\arcgis\desktop10.5\ArcToolbox\Toolboxes\Data Management Tools.tbx\CalculateField" Date="20200601" Time="085416">CalculateField MPM_FuenteCensal_2018 IEE_TOT [Inadecuada] VB #</Process><Process ToolSource="c:\program files (x86)\arcgis\desktop10.5\ArcToolbox\Toolboxes\Data Management Tools.tbx\CalculateField" Date="20200601" Time="085428">CalculateField MPM_FuenteCensal_2018 IEE_CAB [Inasiste_1] VB #</Process><Process ToolSource="c:\program files (x86)\arcgis\desktop10.5\ArcToolbox\Toolboxes\Data Management Tools.tbx\CalculateField" Date="20200601" Time="085444">CalculateField MPM_FuenteCensal_2018 IEE_CPRD [Inadecua_2] VB #</Process><Process ToolSource="c:\program files (x86)\arcgis\desktop10.5\ArcToolbox\Toolboxes\Data Management Tools.tbx\CalculateField" Date="20200601" Time="085459">CalculateField MPM_FuenteCensal_2018 IE_TOT [Inasistenc] VB #</Process><Process ToolSource="c:\program files (x86)\arcgis\desktop10.5\ArcToolbox\Toolboxes\Data Management Tools.tbx\CalculateField" Date="20200601" Time="085525">CalculateField MPM_FuenteCensal_2018 IE_CAB [Inasiste_1] VB #</Process><Process ToolSource="c:\program files (x86)\arcgis\desktop10.5\ArcToolbox\Toolboxes\Data Management Tools.tbx\CalculateField" Date="20200601" Time="085555">CalculateField MPM_FuenteCensal_2018 IE_CPRD [Inasiste_2] VB #</Process><Process ToolSource="c:\program files (x86)\arcgis\desktop10.5\ArcToolbox\Toolboxes\Data Management Tools.tbx\CalculateField" Date="20200601" Time="085621">CalculateField MPM_FuenteCensal_2018 MIPE_TOT [MatInadecu] VB #</Process><Process ToolSource="c:\program files (x86)\arcgis\desktop10.5\ArcToolbox\Toolboxes\Data Management Tools.tbx\CalculateField" Date="20200601" Time="085636">CalculateField MPM_FuenteCensal_2018 MIPE_CAB [MatInade_1] VB #</Process><Process ToolSource="c:\program files (x86)\arcgis\desktop10.5\ArcToolbox\Toolboxes\Data Management Tools.tbx\CalculateField" Date="20200601" Time="085653">CalculateField MPM_FuenteCensal_2018 MIPE_CPRD [MatInade_2] VB #</Process><Process ToolSource="c:\program files (x86)\arcgis\desktop10.5\ArcToolbox\Toolboxes\Data Management Tools.tbx\CalculateField" Date="20200601" Time="085711">CalculateField MPM_FuenteCensal_2018 MIP_TOT [MatInade_3] VB #</Process><Process ToolSource="c:\program files (x86)\arcgis\desktop10.5\ArcToolbox\Toolboxes\Data Management Tools.tbx\CalculateField" Date="20200601" Time="085726">CalculateField MPM_FuenteCensal_2018 MIP_CAB [MatInade_4] VB #</Process><Process ToolSource="c:\program files (x86)\arcgis\desktop10.5\ArcToolbox\Toolboxes\Data Management Tools.tbx\CalculateField" Date="20200601" Time="085745">CalculateField MPM_FuenteCensal_2018 MIP_CPRD [MatInade_5] VB #</Process><Process ToolSource="c:\program files (x86)\arcgis\desktop10.5\ArcToolbox\Toolboxes\Data Management Tools.tbx\CalculateField" Date="20200601" Time="085759">CalculateField MPM_FuenteCensal_2018 RE_TOT [RezagoEsco] VB #</Process><Process ToolSource="c:\program files (x86)\arcgis\desktop10.5\ArcToolbox\Toolboxes\Data Management Tools.tbx\CalculateField" Date="20200601" Time="085814">CalculateField MPM_FuenteCensal_2018 RE_CAB [RezagoEs_1] VB #</Process><Process ToolSource="c:\program files (x86)\arcgis\desktop10.5\ArcToolbox\Toolboxes\Data Management Tools.tbx\CalculateField" Date="20200601" Time="085830">CalculateField MPM_FuenteCensal_2018 RE_CPRD [RezagoEs_2] VB #</Process><Process ToolSource="c:\program files (x86)\arcgis\desktop10.5\ArcToolbox\Toolboxes\Data Management Tools.tbx\CalculateField" Date="20200601" Time="085931">CalculateField MPM_FuenteCensal_2018 SAFAM_TOT [SinAccesFu] VB #</Process><Process ToolSource="c:\program files (x86)\arcgis\desktop10.5\ArcToolbox\Toolboxes\Data Management Tools.tbx\CalculateField" Date="20200601" Time="085954">CalculateField MPM_FuenteCensal_2018 SAFAM_CAB [SinAcces_1] VB #</Process><Process ToolSource="c:\program files (x86)\arcgis\desktop10.5\ArcToolbox\Toolboxes\Data Management Tools.tbx\CalculateField" Date="20200601" Time="090011">CalculateField MPM_FuenteCensal_2018 SAFAM_CPRD [SinAcces_2] VB #</Process><Process ToolSource="c:\program files (x86)\arcgis\desktop10.5\ArcToolbox\Toolboxes\Data Management Tools.tbx\CalculateField" Date="20200601" Time="090144">CalculateField MPM_FuenteCensal_2018 SAS_TOT [SinAsegurS] VB #</Process><Process ToolSource="c:\program files (x86)\arcgis\desktop10.5\ArcToolbox\Toolboxes\Data Management Tools.tbx\CalculateField" Date="20200601" Time="090203">CalculateField MPM_FuenteCensal_2018 SAS_CAB [SinAsegu_1] VB #</Process><Process ToolSource="c:\program files (x86)\arcgis\desktop10.5\ArcToolbox\Toolboxes\Data Management Tools.tbx\CalculateField" Date="20200601" Time="090221">CalculateField MPM_FuenteCensal_2018 SAS_CPRD [SinAsegu_2] VB #</Process><Process ToolSource="c:\program files (x86)\arcgis\desktop10.5\ArcToolbox\Toolboxes\Data Management Tools.tbx\CalculateField" Date="20200601" Time="090531">CalculateField MPM_FuenteCensal_2018 TRINF_TOT [TrabajoInf] VB #</Process><Process ToolSource="c:\program files (x86)\arcgis\desktop10.5\ArcToolbox\Toolboxes\Data Management Tools.tbx\CalculateField" Date="20200601" Time="090545">CalculateField MPM_FuenteCensal_2018 TRINF_CAB [TrabajoI_1] VB #</Process><Process ToolSource="c:\program files (x86)\arcgis\desktop10.5\ArcToolbox\Toolboxes\Data Management Tools.tbx\CalculateField" Date="20200601" Time="090701">CalculateField MPM_FuenteCensal_2018 TRINF_CPRD [TrabajoI_2] VB #</Process><Process ToolSource="c:\program files (x86)\arcgis\desktop10.5\ArcToolbox\Toolboxes\Data Management Tools.tbx\CalculateField" Date="20200601" Time="090721">CalculateField MPM_FuenteCensal_2018 TRIML_TOT [TrabajoI_3] VB #</Process><Process ToolSource="c:\program files (x86)\arcgis\desktop10.5\ArcToolbox\Toolboxes\Data Management Tools.tbx\CalculateField" Date="20200601" Time="090739">CalculateField MPM_FuenteCensal_2018 TRIML_CAB [TrabajoI_4] VB #</Process><Process ToolSource="c:\program files (x86)\arcgis\desktop10.5\ArcToolbox\Toolboxes\Data Management Tools.tbx\CalculateField" Date="20200601" Time="090755">CalculateField MPM_FuenteCensal_2018 TRIML_CPRD [TrabajoI_5] VB #</Process><Process ToolSource="c:\program files (x86)\arcgis\desktop10.5\ArcToolbox\Toolboxes\Data Management Tools.tbx\CalculateField" Date="20200601" Time="091523">CalculateField MPM_FuenteCensal_2018 IEE_CAB [Inadecua_1] VB #</Process></lineage></DataProperties></Esri></metadata>
